maxs/__init__.py
maxs/__main__.py
maxs/main.py
maxs/updater.py
maxs/handlers/callback_handler.py
maxs/tools/__init__.py
maxs/tools/bitchat.py
maxs/tools/create_subagent.py
maxs/tools/data_viz_tool.py
maxs/tools/dialog.py
maxs/tools/event_bridge.py
maxs/tools/fetch_github_tool.py
maxs/tools/graph_db_tool.py
maxs/tools/graphql.py
maxs/tools/listen.py
maxs/tools/realistic_speak.py
maxs/tools/s3_memory.py
maxs/tools/scraper.py
maxs/tools/speak_bark.py
maxs/tools/sql_tool.py
maxs/tools/sqlite_memory.py
maxs/tools/store_in_kb.py
maxs/tools/system_prompt.py
maxs/tools/tasks.py
maxs/tools/tcp.py
maxs/tools/tiny.py
maxs/tools/use_github.py
maxs-0.30.0.dist-info/licenses/LICENSE
maxs-0.30.0.dist-info/METADATA
maxs-0.30.0.dist-info/WHEEL
maxs-0.30.0.dist-info/entry_points.txt
maxs-0.30.0.dist-info/top_level.txt
maxs-0.30.0.dist-info/RECORD
