Metadata-Version: 2.4
Name: maxs
Version: 0.30.0
Summary: minimalist ai agent
Author-email: Cagatay Cali <cagataycali@icloud.com>
License: MIT
Project-URL: Homepage, https://github.com/cagataycali/maxs
Project-URL: Repository, https://github.com/cagataycali/maxs
Project-URL: Issues, https://github.com/cagataycali/maxs/issues
Project-URL: Changelog, https://github.com/cagataycali/maxs/blob/main/CHANGELOG.md
Keywords: ai,agent,ollama,strands,local,minimalist
Classifier: Development Status :: 4 - Beta
Classifier: Intended Audience :: Developers
Classifier: License :: OSI Approved :: MIT License
Classifier: Operating System :: OS Independent
Classifier: Programming Language :: Python :: 3
Classifier: Programming Language :: Python :: 3.8
Classifier: Programming Language :: Python :: 3.9
Classifier: Programming Language :: Python :: 3.10
Classifier: Programming Language :: Python :: 3.11
Classifier: Programming Language :: Python :: 3.12
Classifier: Topic :: Scientific/Engineering :: Artificial Intelligence
Classifier: Topic :: Software Development :: Libraries :: Python Modules
Requires-Python: >=3.10
License-File: LICENSE
Requires-Dist: strands-agents
Requires-Dist: strands-agents-tools
Requires-Dist: strands-agents-tools[diagram]
Requires-Dist: strands-agents[a2a]
Requires-Dist: strands-agents[otel]
Requires-Dist: strands-agents[ollama]
Requires-Dist: strands-agents[openai]
Requires-Dist: strands-agents[anthropic]
Requires-Dist: strands-agents[llamaapi]
Requires-Dist: strands-agents[litellm]
Requires-Dist: strands-agents[mistral]
Requires-Dist: prompt_toolkit>=3.0.0
Requires-Dist: packaging
Requires-Dist: toml
Requires-Dist: beautifulsoup4
Requires-Dist: colorama
Requires-Dist: rich
Requires-Dist: halo
Requires-Dist: openai-whisper
Requires-Dist: numpy
Requires-Dist: sounddevice
Requires-Dist: webrtcvad
Requires-Dist: torch>=2.0.0
Requires-Dist: torchaudio>=2.0.0
Requires-Dist: transformers>=4.40.0
Requires-Dist: soundfile
Provides-Extra: dev
Requires-Dist: pytest>=7.0; extra == "dev"
Requires-Dist: black>=22.0; extra == "dev"
Requires-Dist: isort>=5.0; extra == "dev"
Requires-Dist: flake8>=4.0; extra == "dev"
Requires-Dist: mypy>=0.950; extra == "dev"
Provides-Extra: binary
Requires-Dist: pyinstaller>=5.0; extra == "binary"
Dynamic: license-file
